processing_image/__init__.py
processing_image/processing/__init__.py
processing_image/processing/combination.py
processing_image/processing/transformation.py
processing_image/utils/__init__.py
processing_image/utils/io.py
processing_image/utils/plot.py
package_processing_image-0.0.2.dist-info/LICENSE
package_processing_image-0.0.2.dist-info/METADATA
package_processing_image-0.0.2.dist-info/WHEEL
package_processing_image-0.0.2.dist-info/top_level.txt
package_processing_image-0.0.2.dist-info/RECORD
