Metadata-Version: 2.1
Name: package-processing-image
Version: 0.0.2
Summary: Estudos de pacotes - Image Processing 
Home-page: https://github.com/snitraMnolraM/package-processing-Image
Author: Marlon_Martins
License: UNKNOWN
Platform: UNKNOWN
Requires-Python: >=3.8
Requires-Dist: setuptools (~=41.2.0)
Requires-Dist: scikit-image (~=0.18.2)
Requires-Dist: matplotlib (~=3.4.2)
Requires-Dist: numpy (~=1.21.1)
